{
  "bg": ["#11111b", "#11111b"],
  "active": ["#cdd6f4", "#cdd6f4"],
  "inactive": ["#313244", "#313244"],
  "focus": ["#cba6f7", "#cba6f7"],
  "color1": ["#f38ba8", "#f38ba8"],
  "color2": ["#cba6f7", "#cba6f7"],
  "color3": ["#a6e3a1", "#a6e3a1"],
  "color4": ["#fab387", "#fab387"],
  "color5": ["#74c7ec", "#74c7ec"],
  "color6": ["#f5c2e7", "#f5c2e7"],
  "color7": ["#89b4fa", "#89b4fa"],
  "color8": ["#f9e2af", "#f9e2af"],
  "color9": ["#45475a", "#45475a"],
  "wallpaper": "04.jpg 168.jpg"
}
